dynamic_graphs_with_pygame/__init__.py
dynamic_graphs_with_pygame/dyn_graphs.py
dynamic_graphs_with_pygame-1.2.0.dist-info/LICENSE
dynamic_graphs_with_pygame-1.2.0.dist-info/METADATA
dynamic_graphs_with_pygame-1.2.0.dist-info/WHEEL
dynamic_graphs_with_pygame-1.2.0.dist-info/top_level.txt
dynamic_graphs_with_pygame-1.2.0.dist-info/RECORD
